[
  {
    "type": "H5",
    "children": [
      {
        "text": "Product Overview"
      }
    ]
  },
  {
    "type": "paragraph",
    "children": [
      {
        "text": "In dui magna, posuere eget, vestibulum et, tempor auctor, justo. Sed libero. Nulla porta dolor. Etiam feugiat lorem non metus."
      }
    ]
  },
  {
    "type": "paragraph",
    "children": [
      {
        "text": "Donec interdum, metus et hendrerit aliquet, dolor diam sagittis ligula, eget egestas libero turpis vel mi. Fusce fermentum. Nulla sit amet est. Nunc nec neque."
      }
    ]
  }
]